src/__init__.py
src/draggable_line.py
src/gating.py
src/main.py
src/__pycache__/__init__.cpython-310.pyc
src/__pycache__/draggable_line.cpython-310.pyc
src/__pycache__/gating.cpython-310.pyc
src/__pycache__/main.cpython-310.pyc
tests/Results.csv
venv/bin/activate_this.py
gating-0.0.0.dist-info/METADATA
gating-0.0.0.dist-info/WHEEL
gating-0.0.0.dist-info/entry_points.txt
gating-0.0.0.dist-info/top_level.txt
gating-0.0.0.dist-info/RECORD
