Metadata-Version: 2.1
Name: gating
Version: 0.0.0
Summary: Code to perform gating in data from csv tables
Author-email: Luiza Cherobini Pereira <luiza.cp1998@gmail.com>
License: MIT-License
Keywords: gate,graph
Classifier: Programming Language :: Python :: 3
Requires-Python: >=3.7
Requires-Dist: requests
Requires-Dist: matplotlib (==3.7.1)
Requires-Dist: pandas (==1.4.0)
Requires-Dist: seaborn (==0.11.2)
Requires-Dist: importlib-metadata ; python_version < "3.8"
